autogoal/__init__.py
autogoal/__main__.py
autogoal/datasets/__init__.py
autogoal/datasets/abalone.py
autogoal/datasets/cars.py
autogoal/datasets/cifar10.py
autogoal/datasets/dorothea.py
autogoal/datasets/dummy.py
autogoal/datasets/ehealthkd20/__init__.py
autogoal/datasets/ehealthkd20/_encoding.py
autogoal/datasets/ehealthkd20/_tools.py
autogoal/datasets/ehealthkd20/_utils.py
autogoal/datasets/german_credit.py
autogoal/datasets/gisette.py
autogoal/datasets/haha.py
autogoal/datasets/meddocan.py
autogoal/datasets/movie_reviews.py
autogoal/datasets/shuttle.py
autogoal/datasets/wine_quality.py
autogoal/datasets/yeast.py
autogoal/exceptions.py
autogoal/experimental/__init__.py
autogoal/experimental/stacking.py
autogoal/grammar/__init__.py
autogoal/grammar/_base.py
autogoal/grammar/_cfg.py
autogoal/grammar/_functional.py
autogoal/grammar/_graph.py
autogoal/kb/__init__.py
autogoal/kb/_algorithm.py
autogoal/kb/_data.py
autogoal/kb/_semantics.py
autogoal/kb/_utils.py
autogoal/logging/__init__.py
autogoal/ml/__init__.py
autogoal/ml/_automl.py
autogoal/ml/_metalearning.py
autogoal/ml/metrics.py
autogoal/ml/utils.py
autogoal/sampling/__init__.py
autogoal/search/__init__.py
autogoal/search/_base.py
autogoal/search/_learning.py
autogoal/search/_nspge.py
autogoal/search/_pge.py
autogoal/search/_random.py
autogoal/search/utils.py
autogoal/utils/__init__.py
autogoal/utils/_cache.py
autogoal/utils/_dependency_resolver.py
autogoal/utils/_dynamic.py
autogoal/utils/_helpers.py
autogoal/utils/_package_helper.py
autogoal/utils/_process.py
autogoal/utils/_resource.py
autogoal/utils/_storage.py
autogoal-1.0.3.dist-info/WHEEL
autogoal-1.0.3.dist-info/METADATA
autogoal-1.0.3.dist-info/RECORD
