Metadata-Version: 2.1
Name: autogoal
Version: 1.0.3
Summary: Automatic Generation Optimization And Learning
Home-page: https://autogoal.github.io
License: MIT
Author: Suilan Estevez-Velarde
Author-email: suilanestevez@gmail.com
Requires-Python: >=3.9.13,<3.11
Classifier: Development Status :: 3 - Alpha
Classifier: Intended Audience :: Developers
Classifier: Intended Audience :: Science/Research
Classifier: License :: OSI Approved :: MIT License
Classifier: Programming Language :: Python :: 3
Classifier: Programming Language :: Python :: 3.10
Classifier: Topic :: Scientific/Engineering :: Artificial Intelligence
Classifier: Topic :: Software Development :: Code Generators
Requires-Dist: Cython (>=0.29.33,<0.30.0)
Requires-Dist: Deprecated (>=1.2.13,<2.0.0)
Requires-Dist: PyYAML (>=6.0,<7.0)
Requires-Dist: black (>=22.12.0,<23.0.0)
Requires-Dist: dill (>=0.3.6,<0.4.0)
Requires-Dist: enlighten (>=1.11.1,<2.0.0)
Requires-Dist: networkx (>=2.4,<3.0)
Requires-Dist: numpy (>=1.21.6,<2.0.0)
Requires-Dist: pandas (>=1.1.3,<2.0.0)
Requires-Dist: psutil (>=5.9.4,<6.0.0)
Requires-Dist: pydot (>=1.4.2,<2.0.0)
Requires-Dist: pytest (>=7.2.1,<8.0.0)
Requires-Dist: requests (>=2.31.0,<3.0.0)
Requires-Dist: rich (>=13.2.0,<14.0.0)
Requires-Dist: scipy (==1.6)
Requires-Dist: termcolor (>=2.2.0,<3.0.0)
Requires-Dist: toml (>=0.10.2,<0.11.0)
Requires-Dist: tqdm (>=4.64.1,<5.0.0)
Requires-Dist: typer (>=0.7.0,<0.8.0)
Requires-Dist: yamlable (>=1.1.1,<2.0.0)
Project-URL: Documentation, https://autogoal.github.io
Project-URL: Repository, https://github.com/autogoal/autogoal
